[{"title":"【WATCHALONG】Alice in Borderland: Episode 1-3【hololive Indonesia 2nd Generation】","time":"2021-01-26T15:00:00.000Z","streamer":"Anya","guests":[],"link":"https://www.youtube.com/watch?v=83CSjoizcXk","videoId":"83CSjoizcXk","livePreviewImage":"https://img.youtube.com/vi/83CSjoizcXk/mqdefault.jpg","streaming":false},{"time":"2021-01-26T15:05:00.000Z","streamer":"アキロゼ","guests":[],"link":"https://www.youtube.com/watch?v=y_nAoXWnIr0","videoId":"y_nAoXWnIr0","livePreviewImage":"https://img.youtube.com/vi/y_nAoXWnIr0/mqdefault.jpg","streaming":false},{"time":"2021-01-26T17:00:00.000Z","streamer":"赤井はあと","guests":[],"link":"https://www.youtube.com/watch?v=N0vBDacTJ9k","videoId":"N0vBDacTJ9k","livePreviewImage":"https://img.youtube.com/vi/N0vBDacTJ9k/mqdefault.jpg","streaming":false},{"time":"2021-01-26T21:11:00.000Z","streamer":"天音かなた","guests":[],"link":"https://www.youtube.com/watch?v=jMA46qg4MLE","videoId":"jMA46qg4MLE","livePreviewImage":"https://img.youtube.com/vi/jMA46qg4MLE/mqdefault.jpg","streaming":false},{"title":"【 FallGuys 】English Only で 朝からゲーム!?!?!?【アルランディス/ホロスターズ】","time":"2021-01-26T21:30:00.000Z","streamer":"アルランディス","guests":[],"link":"https://www.youtube.com/watch?v=WRfug_cBbMk","videoId":"WRfug_cBbMk","livePreviewImage":"https://img.youtube.com/vi/WRfug_cBbMk/mqdefault.jpg","streaming":false},{"time":"2021-01-26T21:59:00.000Z","streamer":"尾丸ポルカ","guests":[],"link":"https://www.youtube.com/watch?v=Ah8anK7EA14","videoId":"Ah8anK7EA14","livePreviewImage":"https://img.youtube.com/vi/Ah8anK7EA14/mqdefault.jpg","streaming":false},{"title":"【When the Past was Around】愛2【ホロライブ/常闇トワ】","time":"2021-01-27T01:00:00.000Z","streamer":"常闇トワ","guests":[],"link":"https://www.youtube.com/watch?v=kC5iN_oH-uk","videoId":"kC5iN_oH-uk","livePreviewImage":"https://img.youtube.com/vi/kC5iN_oH-uk/mqdefault.jpg","streaming":false},{"title":"【朝活】夕刻ロベルの朝活雑談－水曜日の朝から話す男－【ホロスターズ/夕刻ロベル】","time":"2021-01-27T01:01:00.000Z","streamer":"夕刻ロベル","guests":[],"link":"https://www.youtube.com/watch?v=wFDDFj-LxFM","videoId":"wFDDFj-LxFM","livePreviewImage":"https://img.youtube.com/vi/wFDDFj-LxFM/mqdefault.jpg","streaming":false},{"title":"【Clubhouse 51】 3-Way Chess","time":"2021-01-27T03:59:00.000Z","streamer":"Ina","guests":["Amelia","Kiara"],"link":"https://www.youtube.com/watch?v=wotwlpvCvPg","videoId":"wotwlpvCvPg","livePreviewImage":"https://img.youtube.com/vi/wotwlpvCvPg/mqdefault.jpg","streaming":false},{"time":"2021-01-27T04:00:00.000Z","streamer":"Reine","guests":[],"link":"https://www.youtube.com/watch?v=FhTIk-N8q0o","videoId":"FhTIk-N8q0o","livePreviewImage":"https://img.youtube.com/vi/FhTIk-N8q0o/mqdefault.jpg","streaming":false},{"time":"2021-01-27T04:30:00.000Z","streamer":"獅白ぼたん","guests":[],"link":"https://www.youtube.com/watch?v=QR_9KzgdEu0","videoId":"QR_9KzgdEu0","livePreviewImage":"https://img.youtube.com/vi/QR_9KzgdEu0/mqdefault.jpg","streaming":false},{"title":"【KARAOKE】A SINGING ZOMBIE IDOL【Hololive Indonesia 2nd Gen】","time":"2021-01-27T08:27:00.000Z","streamer":"Ollie","guests":[],"link":"https://www.youtube.com/watch?v=DdQm4ajNpQ4","videoId":"DdQm4ajNpQ4","livePreviewImage":"https://img.youtube.com/vi/DdQm4ajNpQ4/mqdefault.jpg","streaming":false},{"time":"2021-01-27T09:00:00.000Z","streamer":"桃鈴ねね","guests":[],"link":"https://www.youtube.com/watch?v=qJmJmgQuXtM","videoId":"qJmJmgQuXtM","livePreviewImage":"https://img.youtube.com/vi/qJmJmgQuXtM/mqdefault.jpg","streaming":false},{"title":"【Papers, Please】エンドレスモードでモリモリ審査!!!!【ホロライブ/白上フブキ】","time":"2021-01-27T09:00:00.000Z","streamer":"白上フブキ","guests":[],"link":"https://www.youtube.com/watch?v=zFaFoOiefYY","videoId":"zFaFoOiefYY","livePreviewImage":"https://img.youtube.com/vi/zFaFoOiefYY/mqdefault.jpg","streaming":false},{"time":"2021-01-27T09:00:00.000Z","streamer":"アルランディス","guests":[],"link":"https://www.youtube.com/watch?v=IqHfX0xoau8","videoId":"IqHfX0xoau8","livePreviewImage":"https://img.youtube.com/vi/IqHfX0xoau8/mqdefault.jpg","streaming":false},{"time":"2021-01-27T09:03:00.000Z","streamer":"花咲みやび","guests":["アルランディス","岸堂天真"],"link":"https://www.youtube.com/watch?v=_fgD6B-EvFs","videoId":"_fgD6B-EvFs","livePreviewImage":"https://img.youtube.com/vi/_fgD6B-EvFs/mqdefault.jpg","streaming":false},{"time":"2021-01-27T09:58:00.000Z","streamer":"ロボ子さん","guests":[],"link":"https://www.youtube.com/watch?v=zRtLoKzAbu0","videoId":"zRtLoKzAbu0","livePreviewImage":"https://img.youtube.com/vi/zRtLoKzAbu0/mqdefault.jpg","streaming":false},{"title":"【マリオカートDX8】視聴者参加型⛪罰ゲームあり求婚会場はこちらだにぇ！！【ホロライブ/さくらみこ】","time":"2021-01-27T10:01:00.000Z","streamer":"さくらみこ","guests":[],"link":"https://www.youtube.com/watch?v=plFYw8LkkZg","videoId":"plFYw8LkkZg","livePreviewImage":"https://img.youtube.com/vi/plFYw8LkkZg/mqdefault.jpg","streaming":false},{"time":"2021-01-27T10:59:00.000Z","streamer":"宝鐘マリン","guests":[],"link":"https://www.youtube.com/watch?v=joOcWGNigac","videoId":"joOcWGNigac","livePreviewImage":"https://img.youtube.com/vi/joOcWGNigac/mqdefault.jpg","streaming":false},{"title":"【男性キー】アンコール  / YOASOBI Covered by 律可","time":"2021-01-27T11:00:00.000Z","streamer":"律可","guests":[],"link":"https://www.youtube.com/watch?v=A8udlo9FfPY","videoId":"A8udlo9FfPY","livePreviewImage":"https://img.youtube.com/vi/A8udlo9FfPY/mqdefault.jpg","streaming":false},{"time":"2021-01-27T11:21:00.000Z","streamer":"尾丸ポルカ","guests":[],"link":"https://www.youtube.com/watch?v=XQJ9q0DYbFg","videoId":"XQJ9q0DYbFg","livePreviewImage":"https://img.youtube.com/vi/XQJ9q0DYbFg/mqdefault.jpg","streaming":false},{"time":"2021-01-27T11:27:00.000Z","streamer":"Ollie","guests":[],"link":"https://www.youtube.com/watch?v=ONT69QjsARY","videoId":"ONT69QjsARY","livePreviewImage":"https://img.youtube.com/vi/ONT69QjsARY/mqdefault.jpg","streaming":false},{"time":"2021-01-27T11:35:00.000Z","streamer":"さくらみこ","guests":[],"link":"https://www.youtube.com/watch?v=HeQCex0ByFg","videoId":"HeQCex0ByFg","livePreviewImage":"https://img.youtube.com/vi/HeQCex0ByFg/mqdefault.jpg","streaming":false},{"time":"2021-01-27T11:59:00.000Z","streamer":"尾丸ポルカ","guests":[],"link":"https://www.youtube.com/watch?v=zlr8zctpJV4","videoId":"zlr8zctpJV4","livePreviewImage":"https://img.youtube.com/vi/zlr8zctpJV4/mqdefault.jpg","streaming":false},{"title":"【Hidden Folks】おい！！探すで！！！！【ホロスターズ/夕刻ロベル】","time":"2021-01-27T12:00:00.000Z","streamer":"夕刻ロベル","guests":[],"link":"https://www.youtube.com/watch?v=iWC6YDbWYoE","videoId":"iWC6YDbWYoE","livePreviewImage":"https://img.youtube.com/vi/iWC6YDbWYoE/mqdefault.jpg","streaming":false},{"time":"2021-01-27T12:00:00.000Z","streamer":"ときのそら","guests":["さくらみこ"],"link":"https://www.youtube.com/watch?v=T3lNQRaqZNs","videoId":"T3lNQRaqZNs","livePreviewImage":"https://img.youtube.com/vi/T3lNQRaqZNs/mqdefault.jpg","streaming":false},{"title":"【Skyrim】Part 3 - You're a wizard, Moona.【Moona】","time":"2021-01-27T12:00:00.000Z","streamer":"Moona","guests":[],"link":"https://www.youtube.com/watch?v=qUBC49IoW1o","videoId":"qUBC49IoW1o","livePreviewImage":"https://img.youtube.com/vi/qUBC49IoW1o/mqdefault.jpg","streaming":false},{"time":"2021-01-27T12:01:00.000Z","streamer":"Kiara","guests":[],"link":"https://www.youtube.com/watch?v=bFgkZGRIQoU","videoId":"bFgkZGRIQoU","livePreviewImage":"https://img.youtube.com/vi/bFgkZGRIQoU/mqdefault.jpg","streaming":false},{"title":"【GTAⅤ】カジノでぼろ儲け!!! / CASINO【ホロライブ / 星街すいせい】","time":"2021-01-27T12:05:00.000Z","streamer":"星街すいせい","guests":[],"link":"https://www.youtube.com/watch?v=a8Jot8QDIFI","videoId":"a8Jot8QDIFI","livePreviewImage":"https://img.youtube.com/vi/a8Jot8QDIFI/mqdefault.jpg","streaming":false},{"title":"世界一恥ずかしい耐久","time":"2021-01-27T12:05:00.000Z","streamer":"赤井はあと","guests":[],"link":"https://www.youtube.com/watch?v=PvjN-CiT1UI","videoId":"PvjN-CiT1UI","livePreviewImage":"https://img.youtube.com/vi/PvjN-CiT1UI/mqdefault.jpg","streaming":false},{"title":"【Mother Simulator】俺はPAPAであり、同時にMAMAでもある【アルランディス/ホロスターズ】","time":"2021-01-27T13:01:00.000Z","streamer":"アルランディス","guests":[],"link":"https://www.youtube.com/watch?v=ISoO-IpV-cQ","videoId":"ISoO-IpV-cQ","livePreviewImage":"https://img.youtube.com/vi/ISoO-IpV-cQ/mqdefault.jpg","streaming":false},{"time":"2021-01-27T13:01:00.000Z","streamer":"ロボ子さん","guests":[],"link":"https://www.youtube.com/watch?v=mPmc4x9GnAI","videoId":"mPmc4x9GnAI","livePreviewImage":"https://img.youtube.com/vi/mPmc4x9GnAI/mqdefault.jpg","streaming":false},{"title":"【スプラトゥーン2】FAMSvsOKBR　スプラトゥーン2でわちゃわちゃ!!【FAMS視点】","time":"2021-01-27T13:11:00.000Z","streamer":"白上フブキ","guests":["百鬼あやめ","大空スバル","大神ミオ","猫又おかゆ","戌神ころね","獅白ぼたん","雪花ラミィ"],"link":"https://www.youtube.com/watch?v=UgvSq9eQBvk","videoId":"UgvSq9eQBvk","livePreviewImage":"https://img.youtube.com/vi/UgvSq9eQBvk/mqdefault.jpg","streaming":false},{"time":"2021-01-27T13:12:00.000Z","streamer":"戌神ころね","guests":["百鬼あやめ","大空スバル","大神ミオ","猫又おかゆ","白上フブキ","雪花ラミィ","獅白ぼたん"],"link":"https://www.youtube.com/watch?v=FYMpZ9aWxxQ","videoId":"FYMpZ9aWxxQ","livePreviewImage":"https://img.youtube.com/vi/FYMpZ9aWxxQ/mqdefault.jpg","streaming":false},{"title":"【APEX】初PAD！操作方法なにもわからんブロンズ！【ホロライブ/夏色まつり】","time":"2021-01-27T13:58:00.000Z","streamer":"夏色まつり","guests":[],"link":"https://www.youtube.com/watch?v=ovrbuhF8G54","videoId":"ovrbuhF8G54","livePreviewImage":"https://img.youtube.com/vi/ovrbuhF8G54/mqdefault.jpg","streaming":false},{"time":"2021-01-27T14:00:00.000Z","streamer":"ホロライブ","guests":[],"link":"https://www.youtube.com/watch?v=6sHk3CYD-IA","videoId":"6sHk3CYD-IA","livePreviewImage":"https://img.youtube.com/vi/6sHk3CYD-IA/mqdefault.jpg","streaming":false},{"time":"2021-01-27T14:00:00.000Z","streamer":"角巻わため","guests":[],"link":"https://www.youtube.com/watch?v=mghBi8M7c5w","videoId":"mghBi8M7c5w","livePreviewImage":"https://img.youtube.com/vi/mghBi8M7c5w/mqdefault.jpg","streaming":false},{"title":"【INFLICTION】Definitely Not A Good Idea But At Least Reine's Here【hololive Indonesia 2nd Generation】","time":"2021-01-27T14:00:00.000Z","streamer":"Anya","guests":["Reine"],"link":"https://www.youtube.com/watch?v=ePcXl9H_gLo","videoId":"ePcXl9H_gLo","livePreviewImage":"https://img.youtube.com/vi/ePcXl9H_gLo/mqdefault.jpg","streaming":false},{"time":"2021-01-27T14:08:00.000Z","streamer":"さくらみこ","guests":[],"link":"https://www.youtube.com/watch?v=BejV_UYBMuU","videoId":"BejV_UYBMuU","livePreviewImage":"https://img.youtube.com/vi/BejV_UYBMuU/mqdefault.jpg","streaming":false},{"time":"2021-01-27T14:15:00.000Z","streamer":"不知火フレア","guests":[],"link":"https://www.youtube.com/watch?v=fBqDL9Ot2IA","videoId":"fBqDL9Ot2IA","livePreviewImage":"https://img.youtube.com/vi/fBqDL9Ot2IA/mqdefault.jpg","streaming":false},{"time":"2021-01-27T15:00:00.000Z","streamer":"天音かなた","guests":[],"link":"https://www.youtube.com/watch?v=gfRipnXOrTo","videoId":"gfRipnXOrTo","livePreviewImage":"https://img.youtube.com/vi/gfRipnXOrTo/mqdefault.jpg","streaming":false},{"time":"2021-01-27T15:45:00.000Z","streamer":"荒咬オウガ","guests":[],"link":"https://www.youtube.com/watch?v=5uOvA0_kj_I","videoId":"5uOvA0_kj_I","livePreviewImage":"https://img.youtube.com/vi/5uOvA0_kj_I/mqdefault.jpg","streaming":false},{"title":"【50万人記念枠】ハーフミニオン達成！ありがとう【ホロライブ/癒月ちょこ】","time":"2021-01-27T16:37:00.000Z","streamer":"癒月ちょこ","guests":["癒月ちょこSub"],"link":"https://www.youtube.com/watch?v=17sVW77wahw","videoId":"17sVW77wahw","livePreviewImage":"https://img.youtube.com/vi/17sVW77wahw/mqdefault.jpg","streaming":false},{"title":"【Ark Aberration】恐竜が好きすぎて地下世界ソロ攻略を始める騎士【岸堂天真/ホロスターズ】","time":"2021-01-27T17:07:00.000Z","streamer":"岸堂天真","guests":[],"link":"https://www.youtube.com/watch?v=Gp-GZJ4bts8","videoId":"Gp-GZJ4bts8","livePreviewImage":"https://img.youtube.com/vi/Gp-GZJ4bts8/mqdefault.jpg","streaming":false},{"time":"2021-01-27T18:25:00.000Z","streamer":"白上フブキ","guests":[],"link":"https://www.youtube.com/watch?v=1mDi07WK79g","videoId":"1mDi07WK79g","livePreviewImage":"https://img.youtube.com/vi/1mDi07WK79g/mqdefault.jpg","streaming":false},{"time":"2021-01-27T18:57:00.000Z","streamer":"天音かなた","guests":[],"link":"https://www.youtube.com/watch?v=SBfxq__khC4","videoId":"SBfxq__khC4","livePreviewImage":"https://img.youtube.com/vi/SBfxq__khC4/mqdefault.jpg","streaming":false},{"time":"2021-01-27T23:05:00.000Z","streamer":"Amelia","guests":[],"link":"https://www.youtube.com/watch?v=DtoPcFdbS2k","videoId":"DtoPcFdbS2k","livePreviewImage":"https://img.youtube.com/vi/DtoPcFdbS2k/mqdefault.jpg","streaming":false},{"time":"2021-01-28T00:00:00.000Z","streamer":"尾丸ポルカ","guests":[],"link":"https://www.youtube.com/watch?v=ZDH6SLom1R0","videoId":"ZDH6SLom1R0","livePreviewImage":"https://img.youtube.com/vi/ZDH6SLom1R0/mqdefault.jpg","streaming":false},{"title":"【朝活】夕刻ロベルの朝活雑談－木曜日の朝に起き朝に話す雑談－【ホロスターズ/夕刻ロベル】","time":"2021-01-28T01:00:00.000Z","streamer":"夕刻ロベル","guests":[],"link":"https://www.youtube.com/watch?v=fpPWRXNm4lM","videoId":"fpPWRXNm4lM","livePreviewImage":"https://img.youtube.com/vi/fpPWRXNm4lM/mqdefault.jpg","streaming":false},{"title":"[MINECRAFT] mmm lets build somethin","time":"2021-01-28T01:30:00.000Z","streamer":"Gura","guests":[],"link":"https://www.youtube.com/watch?v=gHuDd_myOUE","videoId":"gHuDd_myOUE","livePreviewImage":"https://img.youtube.com/vi/gHuDd_myOUE/mqdefault.jpg","streaming":false},{"time":"2021-01-28T03:00:00.000Z","streamer":"宝鐘マリン","guests":[],"link":"https://www.youtube.com/watch?v=WeSEiI4iXFA","videoId":"WeSEiI4iXFA","livePreviewImage":"https://img.youtube.com/vi/WeSEiI4iXFA/mqdefault.jpg","streaming":false},{"title":"【マイクラ】思い…だした…【ホロライブ/ロボ子さん】","time":"2021-01-28T05:01:00.000Z","streamer":"ロボ子さん","guests":[],"link":"https://www.youtube.com/watch?v=J6yd9EjLmyk","videoId":"J6yd9EjLmyk","livePreviewImage":"https://img.youtube.com/vi/J6yd9EjLmyk/mqdefault.jpg","streaming":false},{"time":"2021-01-28T05:59:00.000Z","streamer":"天音かなた","guests":[],"link":"https://www.youtube.com/watch?v=nRhgZKw2fnA","videoId":"nRhgZKw2fnA","livePreviewImage":"https://img.youtube.com/vi/nRhgZKw2fnA/mqdefault.jpg","streaming":false},{"time":"2021-01-28T06:00:00.000Z","streamer":"アルランディス","guests":[],"link":"https://www.youtube.com/watch?v=uYSula3BJ4I","videoId":"uYSula3BJ4I","livePreviewImage":"https://img.youtube.com/vi/uYSula3BJ4I/mqdefault.jpg","streaming":false},{"time":"2021-01-28T07:01:00.000Z","streamer":"Calli","guests":[],"link":"https://www.youtube.com/watch?v=cPH8digjMx0","videoId":"cPH8digjMx0","livePreviewImage":"https://img.youtube.com/vi/cPH8digjMx0/mqdefault.jpg","streaming":false},{"time":"2021-01-28T08:15:00.000Z","streamer":"白銀ノエル","guests":[],"link":"https://www.youtube.com/watch?v=TIrQY21PQtc","videoId":"TIrQY21PQtc","livePreviewImage":"https://img.youtube.com/vi/TIrQY21PQtc/mqdefault.jpg","streaming":false},{"time":"2021-01-28T08:28:00.000Z","streamer":"Ollie","guests":[],"link":"https://www.youtube.com/watch?v=raDomGHCBaM","videoId":"raDomGHCBaM","livePreviewImage":"https://img.youtube.com/vi/raDomGHCBaM/mqdefault.jpg","streaming":false},{"title":"【ポケモン剣盾】ポケモン交換したりガチバトル！【潤羽るしあ/ホロライブ】","time":"2021-01-28T09:02:00.000Z","streamer":"潤羽るしあ","guests":[],"link":"https://www.youtube.com/watch?v=ygyv5kfPhAc","videoId":"ygyv5kfPhAc","livePreviewImage":"https://img.youtube.com/vi/ygyv5kfPhAc/mqdefault.jpg","streaming":false},{"title":"【NieR:Automata】完全初見！これは呪いか。それとも罰か、にぇ。【ホロライブ/さくらみこ】","time":"2021-01-28T10:00:00.000Z","streamer":"さくらみこ","guests":[],"link":"https://www.youtube.com/watch?v=FXuewXxMl4s","videoId":"FXuewXxMl4s","livePreviewImage":"https://img.youtube.com/vi/FXuewXxMl4s/mqdefault.jpg","streaming":false},{"title":"【歌枠/song】60万人ありがとうの歌枠！久々なので緊張する～！【獅白ぼたん/ホロライブ】","time":"2021-01-28T11:00:00.000Z","streamer":"獅白ぼたん","guests":[],"link":"https://www.youtube.com/watch?v=2DAeMf8PWxY","videoId":"2DAeMf8PWxY","livePreviewImage":"https://img.youtube.com/vi/2DAeMf8PWxY/mqdefault.jpg","streaming":false},{"title":"【サクラ革命】新イベント満喫＆ガチャ並走!!【ホロライブ/宝鐘マリン・白上フブキ】","time":"2021-01-28T11:00:00.000Z","streamer":"宝鐘マリン","guests":[],"link":"https://www.youtube.com/watch?v=G6z7zkbzdAQ","videoId":"G6z7zkbzdAQ","livePreviewImage":"https://img.youtube.com/vi/G6z7zkbzdAQ/mqdefault.jpg","streaming":false},{"time":"2021-01-28T11:00:00.000Z","streamer":"アルランディス","guests":[],"link":"https://www.youtube.com/watch?v=S9pUg2liH4c","videoId":"S9pUg2liH4c","livePreviewImage":"https://img.youtube.com/vi/S9pUg2liH4c/mqdefault.jpg","streaming":false},{"time":"2021-01-28T11:01:00.000Z","streamer":"ときのそら","guests":[],"link":"https://www.youtube.com/watch?v=5VN72_x_aI8","videoId":"5VN72_x_aI8","livePreviewImage":"https://img.youtube.com/vi/5VN72_x_aI8/mqdefault.jpg","streaming":false},{"time":"2021-01-28T11:58:00.000Z","streamer":"Ollie","guests":[],"link":"https://www.youtube.com/watch?v=aZhHsM4WpMc","videoId":"aZhHsM4WpMc","livePreviewImage":"https://img.youtube.com/vi/aZhHsM4WpMc/mqdefault.jpg","streaming":false},{"title":"【渋谷ハルカスタム】初めましてのメンツですが('ω')【パカエル/季咲あんこ/夏色まつり】","time":"2021-01-28T11:58:00.000Z","streamer":"夏色まつり","guests":[],"link":"https://www.youtube.com/watch?v=S6_R3s5v0qY","videoId":"S6_R3s5v0qY","livePreviewImage":"https://img.youtube.com/vi/S6_R3s5v0qY/mqdefault.jpg","streaming":false},{"title":"【hololiveID】#2 WHEN WARDEN BECOMES AN IMMIGRANT OFFICER !!! 【Ayunda Risu】","time":"2021-01-28T12:00:00.000Z","streamer":"Risu","guests":["Moona","Iofi"],"link":"https://www.youtube.com/watch?v=B1wz3fvyJNA","videoId":"B1wz3fvyJNA","livePreviewImage":"https://img.youtube.com/vi/B1wz3fvyJNA/mqdefault.jpg","streaming":true},{"title":"【歌枠】みんなおひさし！！！！！！！！！！！！ぺこ！【ホロライブ/兎田ぺこら】","time":"2021-01-28T12:01:00.000Z","streamer":"兎田ぺこら","guests":[],"link":"https://www.youtube.com/watch?v=xcPx-vFDtjE","videoId":"xcPx-vFDtjE","livePreviewImage":"https://img.youtube.com/vi/xcPx-vFDtjE/mqdefault.jpg","streaming":false},{"time":"2021-01-28T12:02:00.000Z","streamer":"律可","guests":[],"link":"https://www.youtube.com/watch?v=G45zkC0UvcU","videoId":"G45zkC0UvcU","livePreviewImage":"https://img.youtube.com/vi/G45zkC0UvcU/mqdefault.jpg","streaming":false},{"title":"【NieR:Automata】Let's start a MACHINE WAR!!!!!!! #kfp #キアライブ","time":"2021-01-28T12:30:00.000Z","streamer":"Kiara","guests":[],"link":"https://www.youtube.com/watch?v=fN4bM5RU2wY","videoId":"fN4bM5RU2wY","livePreviewImage":"https://img.youtube.com/vi/fN4bM5RU2wY/mqdefault.jpg","streaming":true},{"title":"【Papers, Please】通りたいの？いいよ～～【猫又おかゆ/ホロライブ】","time":"2021-01-28T12:58:00.000Z","streamer":"猫又おかゆ","guests":[],"link":"https://www.youtube.com/watch?v=ZK1GXnz-1Lw","videoId":"ZK1GXnz-1Lw","livePreviewImage":"https://img.youtube.com/vi/ZK1GXnz-1Lw/mqdefault.jpg","streaming":true},{"title":"【MOONA x REINE】Building holoID Shop with #PavoNova【hololiveID 2nd generation】","time":"2021-01-28T13:00:00.000Z","streamer":"Reine","guests":["Moona"],"link":"https://www.youtube.com/watch?v=aGlQVQ8Tmbw","videoId":"aGlQVQ8Tmbw","livePreviewImage":"https://img.youtube.com/vi/aGlQVQ8Tmbw/mqdefault.jpg","streaming":true},{"title":"【Minecraft】Building holoID Shop【PavoNova】","time":"2021-01-28T13:00:00.000Z","streamer":"Moona","guests":["Reine"],"link":"https://www.youtube.com/watch?v=dcwrJeI7cVQ","videoId":"dcwrJeI7cVQ","livePreviewImage":"https://img.youtube.com/vi/dcwrJeI7cVQ/mqdefault.jpg","streaming":true},{"title":"【グラブル】ガロンゾ編！！：GRANBLUE FANTASY【ホロライブ/大空スバル】","time":"2021-01-28T13:00:00.000Z","streamer":"大空スバル","guests":[],"link":"https://www.youtube.com/watch?v=2AaCaCoRMB0","videoId":"2AaCaCoRMB0","livePreviewImage":"https://img.youtube.com/vi/2AaCaCoRMB0/mqdefault.jpg","streaming":true},{"title":"皆～！！！！！雑談しよう～！！！！！！久しぶりに君たちと話したい！","time":"2021-01-28T13:00:00.000Z","streamer":"Iofi","guests":[],"link":"https://www.youtube.com/watch?v=zpYIlt6cCII","videoId":"zpYIlt6cCII","livePreviewImage":"https://img.youtube.com/vi/zpYIlt6cCII/mqdefault.jpg","streaming":true},{"title":"【COLLAB】BLONDE \"BOMB\"SHELLS B) #amel","time":"2021-01-28T13:00:00.000Z","streamer":"Amelia","guests":["夜空メル"],"link":"https://www.youtube.com/watch?v=mu2ZPKtWMGY","videoId":"mu2ZPKtWMGY","livePreviewImage":"https://img.youtube.com/vi/mu2ZPKtWMGY/mqdefault.jpg","streaming":true},{"title":"【Phasmophobia】騎士に全力で守ってもらうお化け退治【花咲みやび/岸堂天真】","time":"2021-01-28T13:02:00.000Z","streamer":"花咲みやび","guests":["岸堂天真"],"link":"https://www.youtube.com/watch?v=vqvA1diEhXs","videoId":"vqvA1diEhXs","livePreviewImage":"https://img.youtube.com/vi/vqvA1diEhXs/mqdefault.jpg","streaming":false},{"time":"2021-01-28T13:02:00.000Z","streamer":"岸堂天真","guests":["花咲みやび"],"link":"https://www.youtube.com/watch?v=Uk-haZYjR_o","videoId":"Uk-haZYjR_o","livePreviewImage":"https://img.youtube.com/vi/Uk-haZYjR_o/mqdefault.jpg","streaming":false},{"title":"ぴーーーーーーすっ！！！！！！！！！【湊あくあ/ホロライブ】","time":"2021-01-28T13:02:00.000Z","streamer":"湊あくあ","guests":[],"link":"https://www.youtube.com/watch?v=YSLj7ETWMMM","videoId":"YSLj7ETWMMM","livePreviewImage":"https://img.youtube.com/vi/YSLj7ETWMMM/mqdefault.jpg","streaming":true},{"title":"3Dお披露目振り返り★成人祝★福袋開封★感謝枠【尾丸ポルカ/ホロライブ】","time":"2021-01-28T14:00:00.000Z","streamer":"尾丸ポルカ","guests":[],"link":"https://www.youtube.com/watch?v=Ug_LDuFI_z0","videoId":"Ug_LDuFI_z0","livePreviewImage":"https://img.youtube.com/vi/Ug_LDuFI_z0/mqdefault.jpg","streaming":true},{"title":"【スマブラSP】ひつじ！参戦！！！！よちよちスマブラへようこそ！【角巻わため/ホロライブ４期生】","time":"2021-01-28T14:00:00.000Z","streamer":"角巻わため","guests":[],"link":"https://www.youtube.com/watch?v=vytmuNoruq0","videoId":"vytmuNoruq0","livePreviewImage":"https://img.youtube.com/vi/vytmuNoruq0/mqdefault.jpg","streaming":true},{"title":"130万人いくまでやめられない縄跳び","time":"2021-01-28T14:01:00.000Z","streamer":"戌神ころね","guests":[],"link":"https://www.youtube.com/watch?v=Fqbq3RPXRB8","videoId":"Fqbq3RPXRB8","livePreviewImage":"https://img.youtube.com/vi/Fqbq3RPXRB8/mqdefault.jpg","streaming":true},{"title":"【マインクラフト/Minecraft】地下の箱庭作り！Make a miniature in the basement【ホロライブ/不知火フレア】","time":"2021-01-28T15:00:00.000Z","streamer":"不知火フレア","guests":[],"link":"https://www.youtube.com/watch?v=A1p22EzJEu8","videoId":"A1p22EzJEu8","livePreviewImage":"https://img.youtube.com/vi/A1p22EzJEu8/mqdefault.jpg","streaming":false},{"title":"【Minecraft】Day1/作りたいものみつけた！【ホロライブ/アキロゼ】","time":"2021-01-28T15:00:00.000Z","streamer":"アキロゼ","guests":[],"link":"https://www.youtube.com/watch?v=a-LYF3V5V-w","videoId":"a-LYF3V5V-w","livePreviewImage":"https://img.youtube.com/vi/a-LYF3V5V-w/mqdefault.jpg","streaming":false},{"title":"【歌枠】深夜のお歌！Sing a Song!【ホロライブ/夏色まつり】","time":"2021-01-28T15:00:00.000Z","streamer":"夏色まつり","guests":[],"link":"https://www.youtube.com/watch?v=iYUiSuej5Vs","videoId":"iYUiSuej5Vs","livePreviewImage":"https://img.youtube.com/vi/iYUiSuej5Vs/mqdefault.jpg","streaming":false},{"title":"【 ㊗ 】４５万人祝うのら！！！✨【姫森ルーナ/ホロライブ】","time":"2021-01-28T16:00:00.000Z","streamer":"姫森ルーナ","guests":[],"link":"https://www.youtube.com/watch?v=GGLgFY3OQ_w","videoId":"GGLgFY3OQ_w","livePreviewImage":"https://img.youtube.com/vi/GGLgFY3OQ_w/mqdefault.jpg","streaming":false},{"title":"【#らみらいぶ】金曜日の朝活雑談【1月29日】","time":"2021-01-29T00:00:00.000Z","streamer":"雪花ラミィ","guests":[],"link":"https://www.youtube.com/watch?v=lF3Ghlly3tw","videoId":"lF3Ghlly3tw","livePreviewImage":"https://img.youtube.com/vi/lF3Ghlly3tw/mqdefault.jpg","streaming":false},{"title":"シド「乱舞のメロディ」 / 星街すいせい(Cover)","time":"2021-01-29T10:00:00.000Z","streamer":"星街すいせい","guests":[],"link":"https://www.youtube.com/watch?v=LpkWFnRPd-M","videoId":"LpkWFnRPd-M","livePreviewImage":"https://img.youtube.com/vi/LpkWFnRPd-M/mqdefault.jpg","streaming":false},{"title":"【Cover】愛して愛して愛して / 奏手イヅル(Kanade Izuru)","time":"2021-01-29T10:00:00.000Z","streamer":"奏手イヅル","guests":[],"link":"https://www.youtube.com/watch?v=P1GH-04ebzo","videoId":"P1GH-04ebzo","livePreviewImage":"https://img.youtube.com/vi/P1GH-04ebzo/mqdefault.jpg","streaming":false},{"title":"【のりプロ身体測定】姫咲ゆずる様診察いたします！【姫咲ゆずる/ホロライブ/癒月ちょこ】","time":"2021-01-29T11:00:00.000Z","streamer":"癒月ちょこ","guests":["癒月ちょこSub"],"link":"https://www.youtube.com/watch?v=m7aOWCPe3Hg","videoId":"m7aOWCPe3Hg","livePreviewImage":"https://img.youtube.com/vi/m7aOWCPe3Hg/mqdefault.jpg","streaming":false},{"title":"私たちの日常に潜むお題にチャレンジ！【#ホロライブアイドル道】","time":"2021-01-29T11:00:00.000Z","streamer":"ホロライブ","guests":[],"link":"https://www.youtube.com/watch?v=nHZZsT9sAJY","videoId":"nHZZsT9sAJY","livePreviewImage":"https://img.youtube.com/vi/nHZZsT9sAJY/mqdefault.jpg","streaming":false}]